{
  "id": "4886247",
  "name": "Fs-BizFlow系统",
  "font_family": "iconfont",
  "css_prefix_text": "icon-",
  "description": "",
  "glyphs": [
    {
      "icon_id": "47777237",
      "name": "会议管理",
      "font_class": "a-huiyiguanli2",
      "unicode": "e682",
      "unicode_decimal": 59010
    },
    {
      "icon_id": "47777183",
      "name": "等级定义",
      "font_class": "dengjidingyi",
      "unicode": "e67b",
      "unicode_decimal": 59003
    },
    {
      "icon_id": "47777184",
      "name": "阶段性目标及里程碑",
      "font_class": "jieduanxingmubiaojilichengbei",
      "unicode": "e67c",
      "unicode_decimal": 59004
    },
    {
      "icon_id": "47777198",
      "name": "资料管理",
      "font_class": "ziliaoguanli",
      "unicode": "e67d",
      "unicode_decimal": 59005
    },
    {
      "icon_id": "47777199",
      "name": "销售里程碑拆解",
      "font_class": "xiaoshoulichengbeichaijie",
      "unicode": "e67e",
      "unicode_decimal": 59006
    },
    {
      "icon_id": "47777200",
      "name": "项目关键成功指标",
      "font_class": "xiangmuguanjianchenggongzhibiao",
      "unicode": "e67f",
      "unicode_decimal": 59007
    },
    {
      "icon_id": "47777201",
      "name": "组织架构",
      "font_class": "zuzhijiagou",
      "unicode": "e680",
      "unicode_decimal": 59008
    },
    {
      "icon_id": "47777202",
      "name": "审批汇报",
      "font_class": "shenpihuibao",
      "unicode": "e681",
      "unicode_decimal": 59009
    },
    {
      "icon_id": "47575400",
      "name": "英文",
      "font_class": "a-yingwen1",
      "unicode": "e675",
      "unicode_decimal": 58997
    },
    {
      "icon_id": "47575399",
      "name": "中文",
      "font_class": "a-zhongwen3",
      "unicode": "e67a",
      "unicode_decimal": 59002
    },
    {
      "icon_id": "47334748",
      "name": "转需求",
      "font_class": "a-rongqi1",
      "unicode": "e672",
      "unicode_decimal": 58994
    },
    {
      "icon_id": "46937599",
      "name": "一键提交",
      "font_class": "yijian",
      "unicode": "e66f",
      "unicode_decimal": 58991
    },
    {
      "icon_id": "46890846",
      "name": "运费成本管理",
      "font_class": "a-rongqi512",
      "unicode": "e66e",
      "unicode_decimal": 58990
    },
    {
      "icon_id": "46777817",
      "name": "升级模板",
      "font_class": "a-rongqi1787",
      "unicode": "e66d",
      "unicode_decimal": 58989
    },
    {
      "icon_id": "46762975",
      "name": "状态",
      "font_class": "zhuangtai",
      "unicode": "e66c",
      "unicode_decimal": 58988
    },
    {
      "icon_id": "46708116",
      "name": "看板管理",
      "font_class": "a-rongqi1346",
      "unicode": "e66b",
      "unicode_decimal": 58987
    },
    {
      "icon_id": "46704589",
      "name": "复制到",
      "font_class": "a-zu5495",
      "unicode": "e66a",
      "unicode_decimal": 58986
    },
    {
      "icon_id": "46704577",
      "name": "配置",
      "font_class": "tubiao_shezhi",
      "unicode": "e668",
      "unicode_decimal": 58984
    },
    {
      "icon_id": "46704582",
      "name": "重命名",
      "font_class": "a-1xian_1zhuangtailei_bianji",
      "unicode": "e669",
      "unicode_decimal": 58985
    },
    {
      "icon_id": "46582782",
      "name": "收起",
      "font_class": "shouqi",
      "unicode": "e666",
      "unicode_decimal": 58982
    },
    {
      "icon_id": "46582781",
      "name": "展开",
      "font_class": "zhankai",
      "unicode": "e667",
      "unicode_decimal": 58983
    },
    {
      "icon_id": "27714236",
      "name": "图标_箭头左",
      "font_class": "tubiao_jiantouzuo",
      "unicode": "e71a",
      "unicode_decimal": 59162
    },
    {
      "icon_id": "46223661",
      "name": "已延期",
      "font_class": "servicexitong_caogaozhuangtai",
      "unicode": "e659",
      "unicode_decimal": 58969
    },
    {
      "icon_id": "46223566",
      "name": "已延期",
      "font_class": "yiyanqi",
      "unicode": "e658",
      "unicode_decimal": 58968
    },
    {
      "icon_id": "46165767",
      "name": "批量执行",
      "font_class": "piliangzhihang",
      "unicode": "e657",
      "unicode_decimal": 58967
    },
    {
      "icon_id": "46165384",
      "name": "基本信息",
      "font_class": "jibenxinxi",
      "unicode": "e61b",
      "unicode_decimal": 58907
    },
    {
      "icon_id": "46165385",
      "name": "暂停",
      "font_class": "zanting",
      "unicode": "e61c",
      "unicode_decimal": 58908
    },
    {
      "icon_id": "46165569",
      "name": "删除",
      "font_class": "shanchu",
      "unicode": "e61d",
      "unicode_decimal": 58909
    },
    {
      "icon_id": "46165583",
      "name": "完成",
      "font_class": "tubiao_chenggong",
      "unicode": "e61e",
      "unicode_decimal": 58910
    },
    {
      "icon_id": "46165584",
      "name": "终止",
      "font_class": "tubiao_shanchu",
      "unicode": "e651",
      "unicode_decimal": 58961
    },
    {
      "icon_id": "46165664",
      "name": "全屏展开",
      "font_class": "quanpingzhankai",
      "unicode": "e652",
      "unicode_decimal": 58962
    },
    {
      "icon_id": "46165715",
      "name": "同步多维数据",
      "font_class": "zhuanhuan1",
      "unicode": "e653",
      "unicode_decimal": 58963
    },
    {
      "icon_id": "46165722",
      "name": "批量评审",
      "font_class": "shenheceshijieguo",
      "unicode": "e654",
      "unicode_decimal": 58964
    },
    {
      "icon_id": "46165741",
      "name": "分配执行人",
      "font_class": "renyuan",
      "unicode": "e655",
      "unicode_decimal": 58965
    },
    {
      "icon_id": "46165747",
      "name": "修改优先级",
      "font_class": "paixu",
      "unicode": "e656",
      "unicode_decimal": 58966
    },
    {
      "icon_id": "46132717",
      "name": "保存",
      "font_class": "baocun",
      "unicode": "e61a",
      "unicode_decimal": 58906
    },
    {
      "icon_id": "46132627",
      "name": "重新提交",
      "font_class": "zhongxintijiao",
      "unicode": "e617",
      "unicode_decimal": 58903
    },
    {
      "icon_id": "46132628",
      "name": "取消",
      "font_class": "quxiao",
      "unicode": "e618",
      "unicode_decimal": 58904
    },
    {
      "icon_id": "46132651",
      "name": "转故障",
      "font_class": "zhuanguzhang",
      "unicode": "e619",
      "unicode_decimal": 58905
    },
    {
      "icon_id": "27714457",
      "name": "图标_刷新2",
      "font_class": "tubiao_shuaxin2",
      "unicode": "e7d8",
      "unicode_decimal": 59352
    },
    {
      "icon_id": "35216702",
      "name": "编辑2",
      "font_class": "bianji2",
      "unicode": "e6ad",
      "unicode_decimal": 59053
    },
    {
      "icon_id": "45996652",
      "name": "已撤回",
      "font_class": "yichehui",
      "unicode": "e615",
      "unicode_decimal": 58901
    },
    {
      "icon_id": "45996651",
      "name": "超时实例被恢复",
      "font_class": "chaoshishilibeihuifu",
      "unicode": "e616",
      "unicode_decimal": 58902
    },
    {
      "icon_id": "35216795",
      "name": "转换",
      "font_class": "zhuanhuan",
      "unicode": "e70a",
      "unicode_decimal": 59146
    },
    {
      "icon_id": "35216729",
      "name": "关联1",
      "font_class": "guanlian1",
      "unicode": "e6c8",
      "unicode_decimal": 59080
    },
    {
      "icon_id": "35216801",
      "name": "提醒",
      "font_class": "tixing",
      "unicode": "e710",
      "unicode_decimal": 59152
    },
    {
      "icon_id": "45767538",
      "name": "回复",
      "font_class": "a-1xian_3gongjulei_xiaoxi",
      "unicode": "e614",
      "unicode_decimal": 58900
    },
    {
      "icon_id": "45731429",
      "name": "打标签",
      "font_class": "dabiaoqian",
      "unicode": "e613",
      "unicode_decimal": 58899
    },
    {
      "icon_id": "45513349",
      "name": "新建标签",
      "font_class": "xinjianbiaoqian",
      "unicode": "e60b",
      "unicode_decimal": 58891
    },
    {
      "icon_id": "18931164",
      "name": "拒绝",
      "font_class": "jujue",
      "unicode": "e665",
      "unicode_decimal": 58981
    },
    {
      "icon_id": "11372757",
      "name": "成功",
      "font_class": "chenggong",
      "unicode": "e8c3",
      "unicode_decimal": 59587
    },
    {
      "icon_id": "11372770",
      "name": "失败",
      "font_class": "shibai",
      "unicode": "e8c5",
      "unicode_decimal": 59589
    },
    {
      "icon_id": "42753309",
      "name": "时间",
      "font_class": "shijian",
      "unicode": "101d2",
      "unicode_decimal": 66002
    },
    {
      "icon_id": "45468593",
      "name": "完成",
      "font_class": "wancheng",
      "unicode": "e60a",
      "unicode_decimal": 58890
    },
    {
      "icon_id": "45468585",
      "name": "查看",
      "font_class": "chakan",
      "unicode": "e609",
      "unicode_decimal": 58889
    },
    {
      "icon_id": "45468582",
      "name": "添加",
      "font_class": "tianjia",
      "unicode": "e608",
      "unicode_decimal": 58888
    },
    {
      "icon_id": "45249083",
      "name": "发送运维审核",
      "font_class": "fasongyunweishenhe",
      "unicode": "e604",
      "unicode_decimal": 58884
    },
    {
      "icon_id": "45249082",
      "name": "代码合并",
      "font_class": "daimahebing",
      "unicode": "e603",
      "unicode_decimal": 58883
    },
    {
      "icon_id": "45249081",
      "name": "请求合并",
      "font_class": "qingqiuhebing",
      "unicode": "e602",
      "unicode_decimal": 58882
    },
    {
      "icon_id": "45249080",
      "name": "取消合并",
      "font_class": "quxiaohebing",
      "unicode": "e601",
      "unicode_decimal": 58881
    },
    {
      "icon_id": "45056877",
      "name": "回滚",
      "font_class": "a-bianzu14beifen",
      "unicode": "e671",
      "unicode_decimal": 58993
    },
    {
      "icon_id": "45056773",
      "name": "删除",
      "font_class": "a-bianzu14",
      "unicode": "e670",
      "unicode_decimal": 58992
    },
    {
      "icon_id": "44823517",
      "name": "已终止",
      "font_class": "a-3weijinhangtubiaobeifen",
      "unicode": "e664",
      "unicode_decimal": 58980
    },
    {
      "icon_id": "44223468",
      "name": "节点-已完成",
      "font_class": "jiedian-yiwancheng",
      "unicode": "e64a",
      "unicode_decimal": 58954
    },
    {
      "icon_id": "44223470",
      "name": "节点-已终止",
      "font_class": "jiedian-yizhongzhi",
      "unicode": "e64d",
      "unicode_decimal": 58957
    },
    {
      "icon_id": "44223472",
      "name": "节点-进行中",
      "font_class": "jiedian-jinhangzhong",
      "unicode": "e64b",
      "unicode_decimal": 58955
    },
    {
      "icon_id": "27714281",
      "name": "图标_记录",
      "font_class": "tubiao_jilu",
      "unicode": "e736",
      "unicode_decimal": 59190
    },
    {
      "icon_id": "27714458",
      "name": "图标_提示",
      "font_class": "tubiao_tishi",
      "unicode": "e7d9",
      "unicode_decimal": 59353
    },
    {
      "icon_id": "45071726",
      "name": "已暂停",
      "font_class": "a-3weijinhangtubiao2",
      "unicode": "e679",
      "unicode_decimal": 59001
    },
    {
      "icon_id": "45071694",
      "name": "已完成",
      "font_class": "a-1yiwanchengtubiao1",
      "unicode": "e678",
      "unicode_decimal": 59000
    },
    {
      "icon_id": "45071476",
      "name": "已撤回/回滚",
      "font_class": "a-bianzu14beifen1",
      "unicode": "e673",
      "unicode_decimal": 58995
    },
    {
      "icon_id": "45071477",
      "name": "已删除",
      "font_class": "a-bianzu141",
      "unicode": "e674",
      "unicode_decimal": 58996
    },
    {
      "icon_id": "45071488",
      "name": "进行中",
      "font_class": "a-2jinhangzhongtubiao",
      "unicode": "e676",
      "unicode_decimal": 58998
    },
    {
      "icon_id": "45071504",
      "name": "已终结",
      "font_class": "a-3weijinhangtubiaobeifen1",
      "unicode": "e677",
      "unicode_decimal": 58999
    },
    {
      "icon_id": "36451441",
      "name": "资料",
      "font_class": "ziliao",
      "unicode": "e76b",
      "unicode_decimal": 59243
    },
    {
      "icon_id": "35216759",
      "name": "箭头下1",
      "font_class": "jiantouxia1",
      "unicode": "e6e6",
      "unicode_decimal": 59110
    },
    {
      "icon_id": "35216764",
      "name": "箭头右2",
      "font_class": "jiantouyou2",
      "unicode": "e6eb",
      "unicode_decimal": 59115
    },
    {
      "icon_id": "35216799",
      "name": "项目管理",
      "font_class": "xiangmuguanli",
      "unicode": "e70e",
      "unicode_decimal": 59150
    },
    {
      "icon_id": "35216719",
      "name": "导出",
      "font_class": "daochu",
      "unicode": "e6be",
      "unicode_decimal": 59070
    },
    {
      "icon_id": "44823497",
      "name": "已冻结",
      "font_class": "a-3weijinhangtubiao",
      "unicode": "e663",
      "unicode_decimal": 58979
    },
    {
      "icon_id": "44791154",
      "name": "时间指示",
      "font_class": "shijianzhishi",
      "unicode": "e662",
      "unicode_decimal": 58978
    },
    {
      "icon_id": "44762519",
      "name": "警告",
      "font_class": "jinggao",
      "unicode": "e661",
      "unicode_decimal": 58977
    },
    {
      "icon_id": "44762441",
      "name": "文档管理",
      "font_class": "wendangguanli1",
      "unicode": "e660",
      "unicode_decimal": 58976
    },
    {
      "icon_id": "44762134",
      "name": "终止",
      "font_class": "zhongzhi",
      "unicode": "e65f",
      "unicode_decimal": 58975
    },
    {
      "icon_id": "44762072",
      "name": "启动",
      "font_class": "bofang2beifen1",
      "unicode": "e65e",
      "unicode_decimal": 58974
    },
    {
      "icon_id": "44762061",
      "name": "播放2",
      "font_class": "bofang2beifen2",
      "unicode": "e65d",
      "unicode_decimal": 58973
    },
    {
      "icon_id": "44762034",
      "name": "复制资源",
      "font_class": "fuzhiziyuan",
      "unicode": "e65c",
      "unicode_decimal": 58972
    },
    {
      "icon_id": "44762021",
      "name": "需求",
      "font_class": "a-bianzu27",
      "unicode": "e65b",
      "unicode_decimal": 58971
    },
    {
      "icon_id": "44761994",
      "name": "记录",
      "font_class": "jilu",
      "unicode": "e65a",
      "unicode_decimal": 58970
    },
    {
      "icon_id": "27714387",
      "name": "查看",
      "font_class": "tubiao_yanjing",
      "unicode": "e79a",
      "unicode_decimal": 59290
    },
    {
      "icon_id": "36451391",
      "name": "评价管理",
      "font_class": "hetongmoban",
      "unicode": "e739",
      "unicode_decimal": 59193
    },
    {
      "icon_id": "35216781",
      "name": "版本管理",
      "font_class": "zuzhi",
      "unicode": "e6fc",
      "unicode_decimal": 59132
    },
    {
      "icon_id": "35216721",
      "name": "完成",
      "font_class": "chenggong1",
      "unicode": "e6c0",
      "unicode_decimal": 59072
    },
    {
      "icon_id": "36451414",
      "name": "故障管理",
      "font_class": "weiwanchengxiangmu",
      "unicode": "e750",
      "unicode_decimal": 59216
    },
    {
      "icon_id": "35216735",
      "name": "箭头上5",
      "font_class": "jiantoushang5",
      "unicode": "e6ce",
      "unicode_decimal": 59086
    },
    {
      "icon_id": "35216746",
      "name": "箭头下5",
      "font_class": "jiantouxia5",
      "unicode": "e6d9",
      "unicode_decimal": 59097
    },
    {
      "icon_id": "35216723",
      "name": "过滤",
      "font_class": "guolv",
      "unicode": "e6c2",
      "unicode_decimal": 59074
    },
    {
      "icon_id": "39251732",
      "name": "图标_高级筛选",
      "font_class": "tubiao_gaojishaixuan",
      "unicode": "e650",
      "unicode_decimal": 58960
    },
    {
      "icon_id": "35216787",
      "name": "下载",
      "font_class": "xiazai",
      "unicode": "e702",
      "unicode_decimal": 59138
    },
    {
      "icon_id": "35216786",
      "name": "系统日志",
      "font_class": "wendangguanli",
      "unicode": "e701",
      "unicode_decimal": 59137
    },
    {
      "icon_id": "35216751",
      "name": "过滤器",
      "font_class": "guolvqi",
      "unicode": "e6de",
      "unicode_decimal": 59102
    },
    {
      "icon_id": "44223486",
      "name": "通知",
      "font_class": "tongzhi",
      "unicode": "e64f",
      "unicode_decimal": 58959
    },
    {
      "icon_id": "44223469",
      "name": "节点-已驳回",
      "font_class": "jiedian-yibohui",
      "unicode": "e64e",
      "unicode_decimal": 58958
    },
    {
      "icon_id": "44223471",
      "name": "节点-未开始",
      "font_class": "jiedian-weikaishi",
      "unicode": "e64c",
      "unicode_decimal": 58956
    },
    {
      "icon_id": "44223462",
      "name": "播放2备份",
      "font_class": "bofang2beifen",
      "unicode": "e648",
      "unicode_decimal": 58952
    },
    {
      "icon_id": "44223461",
      "name": "节点信息",
      "font_class": "jiedianxinxi",
      "unicode": "e649",
      "unicode_decimal": 58953
    },
    {
      "icon_id": "35216777",
      "name": "添加",
      "font_class": "fs_2025041401icon",
      "unicode": "e6f8",
      "unicode_decimal": 59128
    },
    {
      "icon_id": "35216718",
      "name": "撤回",
      "font_class": "fs_2025041103icon",
      "unicode": "e6bd",
      "unicode_decimal": 59069
    },
    {
      "icon_id": "43968853",
      "name": "填充上传",
      "font_class": "fs_2025041102icon",
      "unicode": "e647",
      "unicode_decimal": 58951
    },
    {
      "icon_id": "35216767",
      "name": "上传",
      "font_class": "fs_2025041101icon",
      "unicode": "e6ee",
      "unicode_decimal": 59118
    },
    {
      "icon_id": "43955862",
      "name": "展开",
      "font_class": "fs_2025041005icon",
      "unicode": "e644",
      "unicode_decimal": 58948
    },
    {
      "icon_id": "43955863",
      "name": "拖动",
      "font_class": "fs_2025041004icon",
      "unicode": "e645",
      "unicode_decimal": 58949
    },
    {
      "icon_id": "43955861",
      "name": "折叠",
      "font_class": "fs_2025041003icon",
      "unicode": "e646",
      "unicode_decimal": 58950
    },
    {
      "icon_id": "43951599",
      "name": "编辑",
      "font_class": "fs_2025041002icon",
      "unicode": "e643",
      "unicode_decimal": 58947
    },
    {
      "icon_id": "43951645",
      "name": "关闭",
      "font_class": "fs_2025041001icon",
      "unicode": "e642",
      "unicode_decimal": 58946
    },
    {
      "icon_id": "43948640",
      "name": "组件",
      "font_class": "fs_2025040935icon",
      "unicode": "e641",
      "unicode_decimal": 58945
    },
    {
      "icon_id": "43948564",
      "name": "复制",
      "font_class": "fs_2025040934icon",
      "unicode": "e63e",
      "unicode_decimal": 58942
    },
    {
      "icon_id": "43948565",
      "name": "删除",
      "font_class": "fs_2025040933icon",
      "unicode": "e63f",
      "unicode_decimal": 58943
    },
    {
      "icon_id": "43948571",
      "name": "配置",
      "font_class": "fs_2025040932icon",
      "unicode": "e640",
      "unicode_decimal": 58944
    },
    {
      "icon_id": "43948348",
      "name": "退出",
      "font_class": "fs_2025040931icon",
      "unicode": "e63d",
      "unicode_decimal": 58941
    },
    {
      "icon_id": "43948316",
      "name": "首页",
      "font_class": "fs_2025040930icon",
      "unicode": "e63c",
      "unicode_decimal": 58940
    },
    {
      "icon_id": "43948261",
      "name": "箭头下",
      "font_class": "fs_2025040929icon",
      "unicode": "e638",
      "unicode_decimal": 58936
    },
    {
      "icon_id": "43948259",
      "name": "填充箭头下",
      "font_class": "fs_2025040928icon",
      "unicode": "e63a",
      "unicode_decimal": 58938
    },
    {
      "icon_id": "43948260",
      "name": "填充箭头上",
      "font_class": "fs_2025040927icon",
      "unicode": "e63b",
      "unicode_decimal": 58939
    },
    {
      "icon_id": "43948208",
      "name": "搜索",
      "font_class": "fs_2025040926icon",
      "unicode": "e639",
      "unicode_decimal": 58937
    },
    {
      "icon_id": "43947609",
      "name": "添加",
      "font_class": "fs_2025040925icon",
      "unicode": "e637",
      "unicode_decimal": 58935
    },
    {
      "icon_id": "43947341",
      "name": "清空标签",
      "font_class": "fs_2025040924icon",
      "unicode": "e636",
      "unicode_decimal": 58934
    },
    {
      "icon_id": "43947284",
      "name": "箭头上",
      "font_class": "fs_2025040923icon",
      "unicode": "e635",
      "unicode_decimal": 58933
    },
    {
      "icon_id": "43942091",
      "name": "评分",
      "font_class": "fs_2025040922icon",
      "unicode": "e634",
      "unicode_decimal": 58932
    },
    {
      "icon_id": "43940002",
      "name": "统计报表",
      "font_class": "fs_2025040921icon",
      "unicode": "e630",
      "unicode_decimal": 58928
    },
    {
      "icon_id": "43939998",
      "name": "需求管理",
      "font_class": "fs_2025040920icon",
      "unicode": "e631",
      "unicode_decimal": 58929
    },
    {
      "icon_id": "43940000",
      "name": "评审管理",
      "font_class": "fs_2025040919icon",
      "unicode": "e632",
      "unicode_decimal": 58930
    },
    {
      "icon_id": "43939999",
      "name": "需求知识库",
      "font_class": "fs_2025040918icon",
      "unicode": "e633",
      "unicode_decimal": 58931
    },
    {
      "icon_id": "43940003",
      "name": "评价管理",
      "font_class": "fs_2025040917icon",
      "unicode": "e62e",
      "unicode_decimal": 58926
    },
    {
      "icon_id": "43940001",
      "name": "配置管理",
      "font_class": "fs_2025040916icon",
      "unicode": "e62f",
      "unicode_decimal": 58927
    },
    {
      "icon_id": "43939977",
      "name": "成员",
      "font_class": "fs_2025040915icon",
      "unicode": "e62b",
      "unicode_decimal": 58923
    },
    {
      "icon_id": "43939976",
      "name": "多选",
      "font_class": "fs_2025040914icon",
      "unicode": "e62c",
      "unicode_decimal": 58924
    },
    {
      "icon_id": "43939975",
      "name": "单选",
      "font_class": "fs_2025040913icon",
      "unicode": "e62d",
      "unicode_decimal": 58925
    },
    {
      "icon_id": "43939981",
      "name": "工作台",
      "font_class": "fs_2025040912icon",
      "unicode": "e629",
      "unicode_decimal": 58921
    },
    {
      "icon_id": "43939978",
      "name": "日期",
      "font_class": "fs_2025040911icon",
      "unicode": "e62a",
      "unicode_decimal": 58922
    },
    {
      "icon_id": "43939956",
      "name": "链接",
      "font_class": "fs_2025040910icon",
      "unicode": "e628",
      "unicode_decimal": 58920
    },
    {
      "icon_id": "43939954",
      "name": "数字",
      "font_class": "fs_2025040909icon",
      "unicode": "e626",
      "unicode_decimal": 58918
    },
    {
      "icon_id": "43939912",
      "name": "进度",
      "font_class": "fs_2025040908icon",
      "unicode": "e627",
      "unicode_decimal": 58919
    },
    {
      "icon_id": "43939670",
      "name": "级联多选",
      "font_class": "fs_2025040907icon",
      "unicode": "e624",
      "unicode_decimal": 58916
    },
    {
      "icon_id": "43939667",
      "name": "级联单选",
      "font_class": "fs_2025040906icon",
      "unicode": "e625",
      "unicode_decimal": 58917
    },
    {
      "icon_id": "43939664",
      "name": "单选多选",
      "font_class": "fs_2025040905icon",
      "unicode": "e620",
      "unicode_decimal": 58912
    },
    {
      "icon_id": "43939665",
      "name": "单行文本",
      "font_class": "fs_2025040904icon",
      "unicode": "e621",
      "unicode_decimal": 58913
    },
    {
      "icon_id": "43939663",
      "name": "富文本",
      "font_class": "fs_2025040903icon",
      "unicode": "e622",
      "unicode_decimal": 58914
    },
    {
      "icon_id": "43939662",
      "name": "多行文本",
      "font_class": "fs_2025040902icon",
      "unicode": "e623",
      "unicode_decimal": 58915
    },
    {
      "icon_id": "43939570",
      "name": "下拉单选",
      "font_class": "fs_2025040901icon",
      "unicode": "e61f",
      "unicode_decimal": 58911
    }
  ]
}
